README.md
setup.cfg
setup.py
norm_evolution_network/__init__.py
norm_evolution_network/simulation.py
norm_evolution_network.egg-info/PKG-INFO
norm_evolution_network.egg-info/SOURCES.txt
norm_evolution_network.egg-info/dependency_links.txt
norm_evolution_network.egg-info/requires.txt
norm_evolution_network.egg-info/top_level.txt