Metadata-Version: 2.1
Name: norm-evolution-network
Version: 0.3
Summary: Simulates which strategy evolves when agents are connected with each others via social network
Home-page: https://github.com/ankur-tutlani/norm-evolution-network
Author: ankurtutlani
Author-email: ankur.tutlani@gmail.com
License: MIT
Download-URL: https://github.com/ankur-tutlani/norm-evolution-network/archive/refs/tags/v_03.tar.gz
Keywords: game theory,evolutionary game,social norms,multi-agents,evolution,social network,small world network,connected network,grid network
Platform: UNKNOWN
Classifier: Development Status :: 3 - Alpha
Classifier: Intended Audience :: Developers
Classifier: Topic :: Software Development :: Build Tools
Classifier: License :: OSI Approved :: MIT License
Classifier: Programming Language :: Python :: 3.7
